vcftoolbox/__init__.py
vcftoolbox/__main__.py
vcftoolbox/add_variant_information.py
vcftoolbox/cli.py
vcftoolbox/genotype.py
vcftoolbox/get_file_handle.py
vcftoolbox/get_header.py
vcftoolbox/header_parser.py
vcftoolbox/log.py
vcftoolbox/parse_variant.py
vcftoolbox/prints.py
vcftoolbox/sort.py
vcftoolbox-1.5.1.dist-info/DESCRIPTION.rst
vcftoolbox-1.5.1.dist-info/METADATA
vcftoolbox-1.5.1.dist-info/RECORD
vcftoolbox-1.5.1.dist-info/WHEEL
vcftoolbox-1.5.1.dist-info/entry_points.txt
vcftoolbox-1.5.1.dist-info/metadata.json
vcftoolbox-1.5.1.dist-info/top_level.txt
