Metadata-Version: 2.0
Name: vcftoolbox
Version: 1.5.1
Summary: Tools for manipulating and parsing vcf files
Home-page: http://github.com/moonso/vcftoolbox
Author: Mans Magnusson
Author-email: mans.magnusson@scilifelab.se
License: MIT License
Keywords: vcf,parsing
Platform: UNKNOWN
Classifier: Programming Language :: Python
Classifier: Programming Language :: Python :: 2.7
Classifier: Programming Language :: Python :: 3
Classifier: License :: OSI Approved :: MIT License
Classifier: Development Status :: 4 - Beta
Classifier: Operating System :: MacOS :: MacOS X
Classifier: Operating System :: Unix
Classifier: Intended Audience :: Science/Research
Classifier: Topic :: Scientific/Engineering :: Bio-Informatics
Requires-Dist: click
Requires-Dist: pytest
